hotbrush/__init__.py
hotbrush/api_tools.py
hotbrush/email_tools.py
hotbrush/string_tools.py
hotbrush-0.0.1.dist-info/METADATA
hotbrush-0.0.1.dist-info/WHEEL
hotbrush-0.0.1.dist-info/RECORD
