Metadata-Version: 2.1
Name: hotbrush
Version: 0.0.1
Summary: A collection of tools
Classifier: License :: OSI Approved :: MIT License
Classifier: Operating System :: OS Independent
Classifier: Programming Language :: Python :: 3
Requires-Python: >=3.7
